dabu/__init__.py
dabu-0.1.4.dist-info/LICENSE.txt
dabu-0.1.4.dist-info/METADATA
dabu-0.1.4.dist-info/WHEEL
dabu-0.1.4.dist-info/top_level.txt
dabu-0.1.4.dist-info/RECORD
