Metadata-Version: 2.1
Name: dabu
Version: 0.1.4
Summary: Dabu facilita la obtencion de datos bursatiles de la Bolsa Mexiana de Valores
Home-page: UNKNOWN
Author: Carlos Crespo Elizondo
Author-email: carlos@dabu.com
License: BSD 3
Keywords: bmv,Bolsa Mexicana de Valores,Analisis fundamental,Precios de cierre
Platform: UNKNOWN
Classifier: Development Status :: 4 - Beta
Classifier: Intended Audience :: Financial and Insurance Industry
Classifier: License :: OSI Approved :: BSD License
Classifier: Programming Language :: Python :: 3.6
Classifier: Programming Language :: Python :: 3.7
Classifier: Programming Language :: Python :: 3.8
Classifier: Programming Language :: Python :: 3.9
Requires-Dist: pandas
Requires-Dist: requests
